velocemu/__init__.py
velocemu/emulator.py
velocemu/utils.py
velocemu/mock_data/mock_error_covariance.npy
velocemu/mock_data/mock_mu_values.npy
velocemu/mock_data/mock_z_values.npy
velocemu/mock_data/mock_z_z_alpha.npy
velocemu/trained_models/dataset_pantheon_moreparams_larger_nonlin_diag.pkl
velocemu/trained_models/dataset_pantheon_moreparams_larger_nonlin_offdiag.pkl
velocemu-0.1.1.dist-info/licenses/LICENSE.txt
velocemu-0.1.1.dist-info/METADATA
velocemu-0.1.1.dist-info/WHEEL
velocemu-0.1.1.dist-info/top_level.txt
velocemu-0.1.1.dist-info/RECORD
