Metadata-Version: 2.4
Name: velocemu
Version: 0.1.1
Summary: The velocity covariance emulator
Home-page: https://github.com/dpiras/veloce
Author: Davide Piras
Author-email: dr.davide.piras@gmail.com
License: GNU General Public License v3.0 (GPLv3)
Classifier: Programming Language :: Python :: 3
Classifier: License :: OSI Approved :: GNU General Public License v3 (GPLv3)
Classifier: Operating System :: OS Independent
Requires-Python: >=3.10
License-File: LICENSE.txt
Requires-Dist: scipy
Requires-Dist: matplotlib
Requires-Dist: numpy
Requires-Dist: jax==0.4.35
Requires-Dist: cosmopower-jax
Requires-Dist: tensorflow==2.13
Requires-Dist: tqdm
Requires-Dist: corner
Dynamic: author
Dynamic: author-email
Dynamic: classifier
Dynamic: description
Dynamic: description-content-type
Dynamic: home-page
Dynamic: license
Dynamic: license-file
Dynamic: requires-dist
Dynamic: requires-python
Dynamic: summary
